insite/__init__.py
insite/cli.py
insite/processor.py
insite/scraper.py
insite-0.1.1.dist-info/licenses/LICENSE
insite-0.1.1.dist-info/METADATA
insite-0.1.1.dist-info/WHEEL
insite-0.1.1.dist-info/entry_points.txt
insite-0.1.1.dist-info/top_level.txt
insite-0.1.1.dist-info/RECORD
