Metadata-Version: 2.4
Name: insite
Version: 0.1.1
Summary: A lightning fast tool for crawling websites and compiling PDFs of their pages
Home-page: https://github.com/heleusbrands/insite
Author: Rose Bloom Research Co
Author-email: rosebloomresearch@gmail.com
License: GPL-3.0-only
Keywords: web crawler,pdf,documentation,scraper,research,insite,bloom research
Classifier: Programming Language :: Python :: 3
Classifier: Programming Language :: Python :: 3.7
Classifier: Programming Language :: Python :: 3.8
Classifier: Programming Language :: Python :: 3.9
Classifier: Programming Language :: Python :: 3.10
Classifier: License :: OSI Approved :: GNU General Public License v3 (GPLv3)
Classifier: Operating System :: OS Independent
Classifier: Topic :: Internet :: WWW/HTTP :: Indexing/Search
Classifier: Topic :: Documentation
Classifier: Topic :: Utilities
Requires-Python: >=3.10
License-File: LICENSE
Requires-Dist: playwright>=1.42.0
Requires-Dist: pypdf>=5.4.0
Requires-Dist: asyncio>=3.4.3
Dynamic: author
Dynamic: author-email
Dynamic: classifier
Dynamic: description
Dynamic: description-content-type
Dynamic: home-page
Dynamic: keywords
Dynamic: license
Dynamic: license-file
Dynamic: requires-dist
Dynamic: requires-python
Dynamic: summary
